spider_env/__init__.py
spider_env/spider_env.py
spider_env-0.0.1.dist-info/METADATA
spider_env-0.0.1.dist-info/WHEEL
spider_env-0.0.1.dist-info/RECORD
