Metadata-Version: 2.1
Name: spider_env
Version: 0.0.1
Requires-Python: >=3.8
Requires-Dist: numpy
